src/UnderstatPlayer.py
src/Utility.py
src/__init__.py
src/constants.py
src/sample.py
tests/__init__.py
tests/test_fbref_player.py
tests/test_imports.py
tests/test_understat_match.py
tests/test_understat_player.py
tests/test_understat_team.py
tests/test_utility.py
xgpy/__init__.py
xgpy/constants.py
xgpy/constants_fbref.py
xgpy/constants_understat.py
xgpy/fbref.py
xgpy/sample.py
xgpy/understat.py
xgpy/utility.py
xgpy-0.0.2.dist-info/COPYING
xgpy-0.0.2.dist-info/METADATA
xgpy-0.0.2.dist-info/WHEEL
xgpy-0.0.2.dist-info/top_level.txt
xgpy-0.0.2.dist-info/RECORD
