Metadata-Version: 2.1
Name: xgpy
Version: 0.0.2
Summary: A Python package to fetch xG data from understat.
Home-page: https://github.com/rkaahean/xgpy
Author: Ranjan Srinivas
Author-email: ranjan310151997@gmail.com
License: UNKNOWN
Platform: UNKNOWN
Classifier: Programming Language :: Python :: 3
Classifier: License :: OSI Approved :: MIT License
Classifier: Operating System :: OS Independent
Requires-Python: >=3.6
Requires-Dist: pytest
Requires-Dist: requests
Requires-Dist: pandas
Requires-Dist: beautifulsoup4
